{
  "identifier": "com.88411.source",
  "name": "88411",
  "subtitle": "Spotify+Youtube",
  "description": "Remove Ads from Spotify, YouTube, and maybe more. ",
  "iconURL": "https://lh3.googleusercontent.com/a/ACg8ocIAzN0NtNLLW6AbT-bBIBZ09FO57UOMIYqaOQ-OtyQVxywme5TJ=s288-c-no",
  "website": "",
  "tintColor": "#e29c56",
  "apps": [
    {
      "name": "Spotify+",
      "bundleIdentifier": "com.88411spotify",
      "developerName": "88411",
      "version": "1.0",
      "versionDate": "2026-04-03T02:52:00-07:00",
      "downloadURL": "https://github.com/88411/sidestoresideloading/releases/download/idk/EeveeSpotify.9.1.12.ipa",
      "localizedDescription": "Spotify with EeveeSpotify features.",
      "iconURL": "https://i.imgur.com/ZHIpWi5.png",
      "tintColor": "#e29c56",
      "size": 89700000,
      "versions": [
        {
          "version": "1.0",
          "date": "2026-04-03T02:52:00-07:00",
          "downloadURL": "https://github.com/88411/sidestoresideloading/releases/download/idk/EeveeSpotify.9.1.12.ipa",
          "size": 89700000
        }
      ]
    },
    {
      "name": "Youtube+",
      "bundleIdentifier": "com.88411youtube",
      "developerName": "88411",
      "version": "1.0",
      "versionDate": "2026-04-03T02:52:00-07:00",
      "downloadURL": "https://github.com/88411/sidestoresideloading/releases/download/idk/YouTubePlus_5.2b4.1.ipa",
      "localizedDescription": "YouTube with Plus features.",
      "iconURL": "https://i.pinimg.com/736x/96/9c/1f/969c1fc84ff0fe941ec48b618f9fbaaf.jpg",
      "tintColor": "#e29c56",
      "size": 123000000,
      "versions": [
        {
          "version": "1.0",
          "date": "2026-04-03T02:52:00-07:00",
          "downloadURL": "https://github.com/88411/sidestoresideloading/releases/download/idk/YouTubePlus_5.2b4.1.ipa",
          "size": 123000000
        }
      ]
    }
  ]
}
